superoptix/__init__.py
superoptix/_protection.py
superoptix/license_protection.py
superoptix/adapters/__init__.py
superoptix/adapters/dspy_adapter.py
superoptix/adapters/framework_registry.py
superoptix/adapters/observability_enhanced_dspy_adapter.py
superoptix/adapters/optimas_openai_adapter.py
superoptix/agent_bases/__init__.py
superoptix/agent_bases/protocol_agent.py
superoptix/agents/README.md
superoptix/agents/agriculture_food/crop_manager_playbook.yaml
superoptix/agents/agriculture_food/food_safety_inspector_playbook.yaml
superoptix/agents/agriculture_food/supply_chain_coordinator_playbook.yaml
superoptix/agents/agriculture_food/sustainability_advisor_playbook.yaml
superoptix/agents/analysis/README.md
superoptix/agents/analysis/sentiment_analyzer_playbook.yaml
superoptix/agents/consulting/business_analyst_playbook.yaml
superoptix/agents/consulting/change_manager_playbook.yaml
superoptix/agents/consulting/performance_consultant_playbook.yaml
superoptix/agents/consulting/process_consultant_playbook.yaml
superoptix/agents/consulting/strategy_consultant_playbook.yaml
superoptix/agents/demo/DEMO_AGENTS_SUMMARY.md
superoptix/agents/demo/MEMORY_OPTIMIZATION_DEMO.md
superoptix/agents/demo/ODSC_CODE_REVIEW_DEMO.md
superoptix/agents/demo/OPENAI_SDK_DEMO.md
superoptix/agents/demo/README.md
superoptix/agents/demo/SETUP.md
superoptix/agents/demo/__init__.py
superoptix/agents/demo/assistant_adk_playbook.yaml
superoptix/agents/demo/assistant_microsoft_playbook.yaml
superoptix/agents/demo/assistant_openai_playbook.yaml
superoptix/agents/demo/chatbot_persistent_playbook.yaml
superoptix/agents/demo/cloud_demo_oracles_playbook.yaml
superoptix/agents/demo/cloud_demo_playbook.yaml
superoptix/agents/demo/code_review_assistant_playbook.yaml
superoptix/agents/demo/code_reviewer_playbook.yaml
superoptix/agents/demo/content_creator_crew_playbook.yaml
superoptix/agents/demo/customer_support_with_memory_playbook.yaml
superoptix/agents/demo/huggingface_demo_playbook.yaml
superoptix-0.2.3.dist-info/METADATA
superoptix-0.2.3.dist-info/WHEEL
superoptix-0.2.3.dist-info/entry_points.txt
superoptix-0.2.3.dist-info/licenses/LICENCE
superoptix-0.2.3.dist-info/RECORD
