Metadata-Version: 2.4
Name: superoptix
Version: 0.2.3
Summary: Full Stack Agentic AI Optimization Framework - Universal GEPA optimizer for major frameworks
Project-URL: Homepage, https://superoptix.ai
Project-URL: Documentation, https://superagenticai.github.io/superoptix-ai
Project-URL: Repository, https://github.com/SuperagenticAI/superoptix-ai
Project-URL: Bug Tracker, https://github.com/SuperagenticAI/superoptix-ai/issues
Project-URL: Support, https://superoptix.ai
Project-URL: Download, https://pypi.org/project/superoptix/#files
Author-email: Superagentic AI <hello@super-agentic.ai>, Shashi Jagtap <shashikant.jagtap@icloud.com>, Shashi Jagtap <shashi@super-agentic.ai>
Maintainer-email: Superagentic AI <hello@super-agentic.ai>
License: Proprietary License
License-File: LICENCE
Keywords: agent-development,agent-framework,agent-memory,agent-observability,agent-orchestration,agent-testing,agents,ai,ai-agents,ai-development,ai-memory,ai-observability,ai-testing,artificial-intelligence,autonomous,bdd,context-engineering,dspy,dspy-ai,evaluation,framework,llm,llm-framework,llm-optimization,machine-learning,memory,multi-agent,observability,optimization,orchestration,prompt-engineering,prompt-optimization,rag,semantic-search,superspec,testing,vector-database
Classifier: Development Status :: 4 - Beta
Classifier: Intended Audience :: Developers
Classifier: Intended Audience :: Science/Research
Classifier: License :: Other/Proprietary License
Classifier: Operating System :: OS Independent
Classifier: Programming Language :: Python :: 3
Classifier: Programming Language :: Python :: 3.11
Classifier: Programming Language :: Python :: 3.12
Classifier: Topic :: Scientific/Engineering :: Artificial Intelligence
Classifier: Topic :: Software Development :: Libraries :: Python Modules
Classifier: Topic :: System :: Distributed Computing
Requires-Python: >=3.11
Requires-Dist: accelerate
Requires-Dist: colorama==0.4.6
Requires-Dist: dspy==3.0.3
Requires-Dist: jinja2==3.1.6
Requires-Dist: litellm<2.0.0,>=1.0.0
Requires-Dist: mcp==1.19.0
Requires-Dist: numpy==2.3.1
Requires-Dist: pydantic>=2.11.9
Requires-Dist: python-dotenv>=1.0.0
Requires-Dist: pyyaml==6.0.2
Requires-Dist: requests==2.32.4
Requires-Dist: rich==14.0.0
Requires-Dist: supabase<3.0.0,>=2.0.0
Requires-Dist: torch>=2.7.1
Requires-Dist: transformers>=4.46.1
Requires-Dist: typer==0.9.0
Provides-Extra: all
Requires-Dist: agent-framework; extra == 'all'
Requires-Dist: azure-identity>=1.15.0; extra == 'all'
Requires-Dist: chromadb<1.2,>=1.1.0; extra == 'all'
Requires-Dist: deepagents>=0.2.0; extra == 'all'
Requires-Dist: dspy==3.0.3; extra == 'all'
Requires-Dist: faiss-cpu==1.11.0; extra == 'all'
Requires-Dist: fastapi==0.116.1; extra == 'all'
Requires-Dist: google-adk==1.17.0; extra == 'all'
Requires-Dist: google-generativeai>=0.8.0; extra == 'all'
Requires-Dist: huggingface-hub>=0.34.0; extra == 'all'
Requires-Dist: lancedb==0.24.0; extra == 'all'
Requires-Dist: langfuse>=2.0.0; extra == 'all'
Requires-Dist: mlflow==3.1.1; extra == 'all'
Requires-Dist: openai-agents==0.4.1; extra == 'all'
Requires-Dist: openai<3,>=2.2; extra == 'all'
Requires-Dist: pandas==2.3.0; extra == 'all'
Requires-Dist: plotly==6.2.0; extra == 'all'
Requires-Dist: pydantic-ai==1.31.0; extra == 'all'
Requires-Dist: pydantic>=2.11.9; extra == 'all'
Requires-Dist: pymilvus==2.5.12; extra == 'all'
Requires-Dist: qdrant-client==1.14.3; extra == 'all'
Requires-Dist: redis>=6.4.0; extra == 'all'
Requires-Dist: sentence-transformers==5.0.0; extra == 'all'
Requires-Dist: streamlit==1.46.1; extra == 'all'
Requires-Dist: torch>=2.7.1; extra == 'all'
Requires-Dist: transformers>=4.46.1; extra == 'all'
Requires-Dist: uvicorn==0.35.0; extra == 'all'
Requires-Dist: weaviate-client==4.15.4; extra == 'all'
Provides-Extra: all-with-mlx
Requires-Dist: agent-framework; extra == 'all-with-mlx'
Requires-Dist: azure-identity>=1.15.0; extra == 'all-with-mlx'
Requires-Dist: chromadb<1.2,>=1.1.0; extra == 'all-with-mlx'
Requires-Dist: deepagents>=0.2.0; extra == 'all-with-mlx'
Requires-Dist: dspy==3.0.3; extra == 'all-with-mlx'
Requires-Dist: faiss-cpu==1.11.0; extra == 'all-with-mlx'
Requires-Dist: fastapi==0.116.1; extra == 'all-with-mlx'
Requires-Dist: google-adk==1.17.0; extra == 'all-with-mlx'
Requires-Dist: google-generativeai>=0.8.0; extra == 'all-with-mlx'
Requires-Dist: huggingface-hub>=0.34.0; extra == 'all-with-mlx'
Requires-Dist: lancedb==0.24.0; extra == 'all-with-mlx'
Requires-Dist: langfuse>=2.0.0; extra == 'all-with-mlx'
Requires-Dist: mlflow==3.1.1; extra == 'all-with-mlx'
Requires-Dist: mlx-lm==0.26.3; extra == 'all-with-mlx'
Requires-Dist: openai-agents==0.4.1; extra == 'all-with-mlx'
Requires-Dist: openai<3,>=2.2; extra == 'all-with-mlx'
Requires-Dist: pandas==2.3.0; extra == 'all-with-mlx'
Requires-Dist: plotly==6.2.0; extra == 'all-with-mlx'
Requires-Dist: pydantic-ai==1.31.0; extra == 'all-with-mlx'
Requires-Dist: pydantic>=2.11.9; extra == 'all-with-mlx'
Requires-Dist: pymilvus==2.5.12; extra == 'all-with-mlx'
Requires-Dist: qdrant-client==1.14.3; extra == 'all-with-mlx'
Requires-Dist: redis>=6.4.0; extra == 'all-with-mlx'
Requires-Dist: sentence-transformers==5.0.0; extra == 'all-with-mlx'
Requires-Dist: streamlit==1.46.1; extra == 'all-with-mlx'
Requires-Dist: torch>=2.7.1; extra == 'all-with-mlx'
Requires-Dist: transformers>=4.46.1; extra == 'all-with-mlx'
Requires-Dist: uvicorn==0.35.0; extra == 'all-with-mlx'
Requires-Dist: weaviate-client==4.15.4; extra == 'all-with-mlx'
Provides-Extra: chromadb
Requires-Dist: chromadb<1.2,>=1.1.0; extra == 'chromadb'
Requires-Dist: sentence-transformers==5.0.0; extra == 'chromadb'
Provides-Extra: cloud
Provides-Extra: data
Provides-Extra: dev
Requires-Dist: black; extra == 'dev'
Requires-Dist: mypy; extra == 'dev'
Requires-Dist: pre-commit; extra == 'dev'
Requires-Dist: pytest; extra == 'dev'
Requires-Dist: pytest-asyncio; extra == 'dev'
Requires-Dist: pytest-cov; extra == 'dev'
Requires-Dist: ruff==0.11.1; extra == 'dev'
Provides-Extra: docs
Requires-Dist: mkdocs-material==9.6.15; extra == 'docs'
Requires-Dist: mkdocs-mermaid2-plugin>=0.6.0; extra == 'docs'
Requires-Dist: mkdocs==1.6.1; extra == 'docs'
Requires-Dist: pymdown-extensions==10.16; extra == 'docs'
Provides-Extra: faiss
Requires-Dist: faiss-cpu==1.11.0; extra == 'faiss'
Requires-Dist: sentence-transformers==5.0.0; extra == 'faiss'
Provides-Extra: frameworks
Requires-Dist: agent-framework; extra == 'frameworks'
Requires-Dist: azure-identity>=1.15.0; extra == 'frameworks'
Requires-Dist: deepagents>=0.2.0; extra == 'frameworks'
Requires-Dist: dspy==3.0.3; extra == 'frameworks'
Requires-Dist: google-adk==1.17.0; extra == 'frameworks'
Requires-Dist: google-generativeai>=0.8.0; extra == 'frameworks'
Requires-Dist: openai-agents==0.4.1; extra == 'frameworks'
Requires-Dist: openai<3,>=2.2; extra == 'frameworks'
Requires-Dist: pydantic-ai==1.31.0; extra == 'frameworks'
Provides-Extra: frameworks-deepagents
Requires-Dist: deepagents>=0.2.0; extra == 'frameworks-deepagents'
Provides-Extra: frameworks-dspy
Requires-Dist: dspy==3.0.3; extra == 'frameworks-dspy'
Provides-Extra: frameworks-google
Requires-Dist: google-adk==1.17.0; extra == 'frameworks-google'
Requires-Dist: google-generativeai>=0.8.0; extra == 'frameworks-google'
Provides-Extra: frameworks-microsoft
Requires-Dist: agent-framework; extra == 'frameworks-microsoft'
Requires-Dist: azure-identity>=1.15.0; extra == 'frameworks-microsoft'
Provides-Extra: frameworks-openai
Requires-Dist: openai-agents==0.4.1; extra == 'frameworks-openai'
Requires-Dist: openai<3,>=2.2; extra == 'frameworks-openai'
Provides-Extra: frameworks-pydantic-ai
Requires-Dist: pydantic-ai==1.31.0; extra == 'frameworks-pydantic-ai'
Provides-Extra: huggingface
Requires-Dist: fastapi==0.116.1; extra == 'huggingface'
Requires-Dist: huggingface-hub>=0.34.0; extra == 'huggingface'
Requires-Dist: torch>=2.7.1; extra == 'huggingface'
Requires-Dist: transformers>=4.46.1; extra == 'huggingface'
Requires-Dist: uvicorn==0.35.0; extra == 'huggingface'
Provides-Extra: lancedb
Requires-Dist: lancedb==0.24.0; extra == 'lancedb'
Requires-Dist: sentence-transformers==5.0.0; extra == 'lancedb'
Provides-Extra: logfire
Requires-Dist: logfire==4.15.0; extra == 'logfire'
Provides-Extra: mcp
Requires-Dist: mcp==1.19.0; extra == 'mcp'
Provides-Extra: milvus
Requires-Dist: pymilvus==2.5.12; extra == 'milvus'
Requires-Dist: sentence-transformers==5.0.0; extra == 'milvus'
Provides-Extra: ml-cross-platform
Requires-Dist: huggingface-hub>=0.34.0; extra == 'ml-cross-platform'
Requires-Dist: torch>=2.7.1; extra == 'ml-cross-platform'
Requires-Dist: transformers>=4.46.1; extra == 'ml-cross-platform'
Provides-Extra: mlx
Requires-Dist: mlx-lm==0.26.3; extra == 'mlx'
Provides-Extra: observability
Requires-Dist: langfuse>=2.0.0; extra == 'observability'
Requires-Dist: mlflow==3.1.1; extra == 'observability'
Requires-Dist: pandas==2.3.0; extra == 'observability'
Requires-Dist: plotly==6.2.0; extra == 'observability'
Provides-Extra: qdrant
Requires-Dist: qdrant-client==1.14.3; extra == 'qdrant'
Requires-Dist: sentence-transformers==5.0.0; extra == 'qdrant'
Provides-Extra: redis
Requires-Dist: redis>=6.4.0; extra == 'redis'
Provides-Extra: testing
Requires-Dist: pytest-asyncio>=0.21.0; extra == 'testing'
Requires-Dist: pytest-cov>=4.0.0; extra == 'testing'
Requires-Dist: pytest-mock>=3.10.0; extra == 'testing'
Requires-Dist: pytest>=7.0.0; extra == 'testing'
Requires-Dist: responses>=0.23.0; extra == 'testing'
Provides-Extra: ui
Requires-Dist: pandas==2.3.0; extra == 'ui'
Requires-Dist: plotly==6.2.0; extra == 'ui'
Requires-Dist: streamlit==1.46.1; extra == 'ui'
Provides-Extra: vectordb
Requires-Dist: chromadb<1.2,>=1.1.0; extra == 'vectordb'
Requires-Dist: faiss-cpu==1.11.0; extra == 'vectordb'
Requires-Dist: lancedb==0.24.0; extra == 'vectordb'
Requires-Dist: pymilvus==2.5.12; extra == 'vectordb'
Requires-Dist: qdrant-client==1.14.3; extra == 'vectordb'
Requires-Dist: sentence-transformers==5.0.0; extra == 'vectordb'
Requires-Dist: weaviate-client==4.15.4; extra == 'vectordb'
Provides-Extra: weaviate
Requires-Dist: sentence-transformers==5.0.0; extra == 'weaviate'
Requires-Dist: weaviate-client==4.15.4; extra == 'weaviate'
Provides-Extra: web
Requires-Dist: fastapi==0.116.1; extra == 'web'
Requires-Dist: pydantic>=2.11.9; extra == 'web'
Requires-Dist: uvicorn==0.35.0; extra == 'web'
